garter/__about__.py
garter/__init__.py
garter/utils/__init__.py
garter/utils/numeric.py
garter-0.0.1.dist-info/LICENSE.txt
garter-0.0.1.dist-info/METADATA
garter-0.0.1.dist-info/WHEEL
garter-0.0.1.dist-info/RECORD
